
{
    "users": [
     
       {
        "name":"muhibprime@gmail.com",
         "password":"123"
       },
       {
        "name":"muhib.k@testyantra.com",
        "password":"123"
       },
       {
          "name":"vikas.k@testyantra.com",
          "password":"vikas@123"
       },
       {
          "name":"hr@testyantra.com",
          "password":"123"
       },
       {
          "name":"hr_ambika@testyantra.com",
          "password":"ambika@123"
       },
       {
          "name":"hr_shwetha@testyantra.com",
          "password":"shwetha@123"
       },
       {
         "name":"vidyasr262@gmail.com",
         "password":"123"
      }

    ]
 }